README.txt
setup.cfg
setup.py
collective/__init__.py
collective.archiveviewer.egg-info/PKG-INFO
collective.archiveviewer.egg-info/SOURCES.txt
collective.archiveviewer.egg-info/dependency_links.txt
collective.archiveviewer.egg-info/entry_points.txt
collective.archiveviewer.egg-info/namespace_packages.txt
collective.archiveviewer.egg-info/not-zip-safe
collective.archiveviewer.egg-info/paster_plugins.txt
collective.archiveviewer.egg-info/requires.txt
collective.archiveviewer.egg-info/top_level.txt
collective/archiveviewer/__init__.py
collective/archiveviewer/adapters.py
collective/archiveviewer/configure.zcml
collective/archiveviewer/interfaces.py
collective/archiveviewer/subscribers.py
collective/archiveviewer/utils.py
collective/archiveviewer/browser/__init__.py
collective/archiveviewer/browser/configure.zcml
collective/archiveviewer/browser/views.py
collective/archiveviewer/profiles/default/metadata.xml
collective/archiveviewer/tests/__init__.py
collective/archiveviewer/tests/base.py
collective/archiveviewer/tests/example.zip
collective/archiveviewer/tests/test_file.html
collective/archiveviewer/tests/test_file.py
collective/archiveviewer/tests/test_file.txt
collective/archiveviewer/tests/folder/other_file.txt
docs/HISTORY.txt
docs/INSTALL.txt
docs/LICENSE.GPL
docs/LICENSE.txt