Metadata-Version: 1.0
Name: collective.archiveviewer
Version: 1.0b2
Summary: Allows to upload archive files (check readme for supported types)       and access their contents trough the web, without having to download and extract them
Home-page: https://github.com/collective/collective.archiveviewer
Author: Simone Orsi [simahawk]
Author-email: simahawk@gmail.com
License: GPL
Platform: UNKNOWN
Classifier: Framework :: Plone
Classifier: Programming Language :: Python
